keep_alive_ping/__init__.py
keep_alive_ping/config.py
keep_alive_ping/service.py
keep_alive_ping-0.0.2.dist-info/LICENSE
keep_alive_ping-0.0.2.dist-info/METADATA
keep_alive_ping-0.0.2.dist-info/WHEEL
keep_alive_ping-0.0.2.dist-info/top_level.txt
keep_alive_ping-0.0.2.dist-info/RECORD
