Metadata-Version: 2.2
Name: keep_alive_ping
Version: 0.0.2
Summary: A robust, production-grade service to keep web applications alive on platforms like Render and Koyeb
Home-page: https://github.com/RKgroupkg/KeepAlive
Author: Rkgroup
Author-email: Rkgroup <rkgroup.coder@gmail.com>
License: MIT
Project-URL: Homepage, https://github.com/RKgroupkg/keepalive
Project-URL: Bug Tracker, https://github.com/RKgroupkg/keepalive/issues
Classifier: Development Status :: 4 - Beta
Classifier: Intended Audience :: Developers
Classifier: License :: OSI Approved :: MIT License
Classifier: Programming Language :: Python :: 3
Classifier: Programming Language :: Python :: 3.7
Classifier: Programming Language :: Python :: 3.8
Classifier: Programming Language :: Python :: 3.9
Classifier: Programming Language :: Python :: 3.10
Classifier: Programming Language :: Python :: 3.11
Requires-Python: >=3.5
License-File: LICENSE
Requires-Dist: Flask>=2.0.0
Requires-Dist: requests>=2.25.0
Requires-Dist: apscheduler>=3.7.0
Requires-Dist: pytz
Provides-Extra: dev
Requires-Dist: pytest>=7.0.0; extra == "dev"
Requires-Dist: black>=22.3.0; extra == "dev"
Requires-Dist: flake8>=4.0.0; extra == "dev"
Requires-Dist: mypy>=0.950; extra == "dev"
Dynamic: author
Dynamic: home-page
Dynamic: requires-python
